amep/__init__.py
amep/_version.py
amep/base.py
amep/cluster.py
amep/continuum.py
amep/evaluate.py
amep/functions.py
amep/load.py
amep/order.py
amep/pbc.py
amep/plot.py
amep/reader.py
amep/spatialcor.py
amep/statistics.py
amep/thermo.py
amep/timecor.py
amep/trajectory.py
amep/utils.py
amep/styles/amep_latex.mplstyle
amep/styles/amep_standard.mplstyle
amep-1.1.1.dist-info/licenses/AUTHORS
amep-1.1.1.dist-info/licenses/LICENSE
amep-1.1.1.dist-info/licenses/LICENSES.third-party
examples/continuum-example.py
examples/particle-example.py
examples/data/continuum/solver.py
amep-1.1.1.dist-info/METADATA
amep-1.1.1.dist-info/WHEEL
amep-1.1.1.dist-info/top_level.txt
amep-1.1.1.dist-info/RECORD
