Metadata-Version: 2.4
Name: amep
Version: 1.1.1
Summary: Active Matter Evaluation Package for data analysis of active matter simulations
Author-email: Lukas Hecht <lukas.hecht@pkm.tu-darmstadt.de>
License:                     GNU GENERAL PUBLIC LICENSE
Project-URL: Homepage, https://amepproject.de/
Project-URL: Issues, https://github.com/amepproject/amep/issues
Project-URL: Repository, https://github.com/amepproject/amep
Project-URL: Documentation, https://amepproject.de/
Project-URL: Source Code, https://github.com/amepproject/amep
Project-URL: Forum, https://github.com/amepproject/amep/discussions
Project-URL: Changelog, https://github.com/amepproject/amep/blob/main/CHANGELOG.md
Keywords: active matter,soft matter,physics,data analysis,computational physics
Classifier: Development Status :: 5 - Production/Stable
Classifier: Intended Audience :: Science/Research
Classifier: Intended Audience :: Education
Classifier: License :: OSI Approved :: GNU General Public License v3 or later (GPLv3+)
Classifier: Natural Language :: English
Classifier: Operating System :: OS Independent
Classifier: Programming Language :: Python :: 3
Classifier: Programming Language :: Python :: 3.10
Classifier: Programming Language :: Python :: 3.11
Classifier: Programming Language :: Python :: 3.12
Classifier: Topic :: Scientific/Engineering :: Physics
Classifier: Topic :: Scientific/Engineering :: Visualization
Requires-Python: >=3.10
License-File: LICENSE
License-File: LICENSES.third-party
License-File: AUTHORS
Requires-Dist: h5py>=3.7.0
Requires-Dist: matplotlib>=3.6.2
Requires-Dist: numba>=0.56.4
Requires-Dist: numpy>=1.21.6
Requires-Dist: scipy>=1.10.0
Requires-Dist: scikit-image>=0.20.0
Requires-Dist: tqdm>=4.65.0
Requires-Dist: gsd>=3.2.0
Requires-Dist: chemfiles>=0.10.4
Provides-Extra: dev
Requires-Dist: setuptools>=64; extra == "dev"
Dynamic: license-file
